kraph/__init__.py
kraph/arkitekt.py
kraph/datalayer.py
kraph/errors.py
kraph/funcs.py
kraph/io.py
kraph/kraph.py
kraph/py.typed
kraph/rath.py
kraph/rekuest.py
kraph/scalars.py
kraph/traits.py
kraph/vars.py
kraph/widgets.py
kraph/api/__init__.py
kraph/api/project.json
kraph/api/schema.graphql
kraph/api/schema.py
kraph/contrib/fakts/__init__.py
kraph/contrib/fakts/datalayer.py
kraph/links/__init__.py
kraph/links/errors.py
kraph/links/upload.py
kraph-0.5.1.dist-info/METADATA
kraph-0.5.1.dist-info/WHEEL
kraph-0.5.1.dist-info/RECORD
