Metadata-Version: 2.4
Name: kraph
Version: 0.5.1
Summary: the arkitekt knowledge graph
Author-email: jhnnsrs <jhnnsrs@gmail.com>
License-Expression: GPL-3.0-or-later
Requires-Python: <4.0,>=3.11
Requires-Dist: dokker>=2.3
Requires-Dist: rath>=3.5
Requires-Dist: websockets>=15.0.1
